purecpp_crawl4ai/__init__.py
purecpp_crawl4ai/loader.py
purecpp_crawl4ai-0.1.0.dist-info/licenses/LICENSE
purecpp_crawl4ai-0.1.0.dist-info/METADATA
purecpp_crawl4ai-0.1.0.dist-info/WHEEL
purecpp_crawl4ai-0.1.0.dist-info/top_level.txt
purecpp_crawl4ai-0.1.0.dist-info/RECORD
