Metadata-Version: 2.4
Name: purecpp-crawl4ai
Version: 0.1.0
Summary: PureCPP Crawl4AI integration
Author-email: Gabriel Ayres <gabriel.ayres@pureai.com.br>
Maintainer-email: Gabriel Ayres <gabriel.ayres@pureai.com.br>
License-Expression: MIT
Requires-Python: >=3.10
License-File: LICENSE
Requires-Dist: asyncio>=3.4.3
Requires-Dist: crawl4ai>=0.7.0
Requires-Dist: purecpp>=0.0.12
Requires-Dist: purecpp-extract>=0.0.12
Requires-Dist: purecpp-libs>=0.0.12
Dynamic: license-file
